{"INFO": [
  {
    "type": "Feature",
    "id": "PathAnnotationObject",
    "geometry": {
      "type": "Polygon",
      "coordinates": [
        [
          [1796, 8562],
          [1723, 10035],
          [1541, 11122],
          [3580, 15925],
          [5348, 17013],
          [4487, 18191],
          [6526, 20184],
          [6435, 22223],
          [10286, 32781],
          [14953, 45377],
          [19938, 54530],
          [23381, 55708],
          [23834, 56932],
          [22883, 60285],
          [22838, 60239],
          [24333, 65450],
          [24786, 70027],
          [26055, 70570],
          [25873, 73198],
          [28773, 77775],
          [32851, 80675],
          [35026, 78953],
          [33168, 77593],
          [33395, 75147],
          [35117, 75283],
          [35162, 77458],
          [36839, 77412],
          [35706, 74150],
          [36612, 73198],
          [36703, 73198],
          [37337, 76053],
          [39376, 73380],
          [41098, 73697],
          [42638, 74739],
          [45765, 74648],
          [49209, 71794],
          [50432, 70887],
          [53332, 68848],
          [59494, 66945],
          [63119, 65359],
          [64342, 65586],
          [76259, 60602],
          [79386, 59650],
          [85820, 56660],
          [94927, 52944],
          [94837, 51630],
          [95834, 51630],
          [97012, 52672],
          [103627, 51041],
          [103582, 50951],
          [102766, 45921],
          [99912, 38807],
          [91393, 33596],
          [90396, 30153],
          [74401, 25259],
          [72589, 24081],
          [71955, 23130],
          [67244, 21743],
          [57772, 20320],
          [51459, 19338],
          [37156, 20260],
          [30269, 18250],
          [26512, 16570],
          [21964, 15317],
          [21898, 15284],
          [15472, 15120],
          [12374, 13604],
          [7991, 10275],
          [2949, 9484],
          [2817, 9484],
          [1796, 8562]
        ]
      ]
    },
    "properties": {
      "classification": {
        "name": "Region*",
        "colorRGB": -16777036
      },
      "isLocked": false,
      "measurements": []
    }
  },
  {
    "type": "Feature",
    "id": "PathAnnotationObject",
    "geometry": {
      "type": "Polygon",
      "coordinates": [
        [
          [12873, 15066],
          [10032, 16824],
          [10012, 16824],
          [10053, 18439],
          [12873, 18316],
          [10605, 20790],
          [12873, 23181],
          [13752, 21158],
          [16062, 19277],
          [17697, 19665],
          [16655, 21362],
          [18331, 23386],
          [21888, 21955],
          [24525, 20095],
          [27632, 21117],
          [30922, 21628],
          [29349, 23161],
          [33518, 26533],
          [35011, 26043],
          [37014, 28659],
          [41000, 29375],
          [45905, 28210],
          [49912, 26779],
          [49994, 25634],
          [47909, 23406],
          [49094, 21975],
          [52962, 20590],
          [51641, 19628],
          [50137, 19727],
          [42737, 20033],
          [42737, 20054],
          [36830, 20647],
          [33682, 19788],
          [29124, 18439],
          [25097, 16599],
          [20150, 15618],
          [14386, 15741],
          [12873, 15066]
        ]
      ]
    },
    "properties": {
      "classification": {
        "name": "Tumor",
        "colorRGB": -3670016
      },
      "isLocked": false,
      "measurements": []
    }
  }
]
}

